setup.py
payment/__init__.py
payment.egg-info/PKG-INFO
payment.egg-info/SOURCES.txt
payment.egg-info/dependency_links.txt
payment.egg-info/requires.txt
payment.egg-info/top_level.txt
payment/amazon/__init__.py
payment/amazon/simplepay.py
payment/paypal/__init__.py