Metadata-Version: 1.1
Name: payment
Version: 0.00.001.02
Summary: Payment gateway library
Home-page: http://cosmosframework.com
Author: Maruf Maniruzzaman
Author-email: marufm@cosmosframework.com
License: MIT License
Platform: UNKNOWN
Classifier: Development Status :: 2 - Pre-Alpha
Classifier: Intended Audience :: Developers
Classifier: Topic :: Software Development :: Libraries :: Application Frameworks
Classifier: License :: OSI Approved :: MIT License
Classifier: Programming Language :: Python :: 2.7
